stochrare/__init__.py
stochrare/edpy.py
stochrare/firstpassage.py
stochrare/fokkerplanck.py
stochrare/timeseries.py
stochrare/utils.py
stochrare/dynamics/__init__.py
stochrare/dynamics/diffusion.py
stochrare/dynamics/diffusion1d.py
stochrare/io/__init__.py
stochrare/io/data.py
stochrare/io/plot.py
stochrare/rare/__init__.py
stochrare/rare/ams.py
stochrare-0.0.1.dist-info/LICENSE
stochrare-0.0.1.dist-info/METADATA
stochrare-0.0.1.dist-info/WHEEL
stochrare-0.0.1.dist-info/top_level.txt
stochrare-0.0.1.dist-info/RECORD
