Metadata-Version: 2.1
Name: stochrare
Version: 0.0.1
Summary: A package to simulate simple stochastic processes
Home-page: https://github.com/cbherbert/stochrare
Author: Corentin Herbert
Author-email: corentin.herbert@ens-lyon.fr
License: UNKNOWN
Platform: UNKNOWN
Classifier: Programming Language :: Python :: 3
Classifier: Programming Language :: Python :: 3.6
Classifier: Programming Language :: Python :: 3.7
Classifier: Operating System :: OS Independent
Classifier: Intended Audience :: Science/Research
Classifier: Intended Audience :: Education
Classifier: Topic :: Scientific/Engineering :: Physics
Classifier: License :: OSI Approved :: GNU General Public License v3 (GPLv3)
Requires-Dist: matplotlib
Requires-Dist: numpy
Requires-Dist: scipy
